tenet/__init__.py
tenet/exceptions.py
tenet/utils.py
tenet-0.6.dist-info/LICENSE
tenet-0.6.dist-info/METADATA
tenet-0.6.dist-info/WHEEL
tenet-0.6.dist-info/top_level.txt
tenet-0.6.dist-info/RECORD
