Metadata-Version: 2.1
Name: tenet
Version: 0.6
Summary: stats.tenet.ua account manager
Home-page: https://github.com/zen-tools/py-tenet
Author: Dmitriy Poltavchenko
Author-email: poltavchenko.dmitriy@gmail.com
License: GPL
Platform: UNKNOWN
Classifier: Topic :: Internet
Classifier: Programming Language :: Python :: 2
Classifier: Programming Language :: Python :: 3
Classifier: License :: OSI Approved :: GNU General Public License v3 (GPLv3)
Classifier: Operating System :: OS Independent
Requires-Dist: requests
Requires-Dist: lxml
